gpr.cpython-36m-darwin.so
gpr-0.0.1.dist-info/DESCRIPTION.rst
gpr-0.0.1.dist-info/METADATA
gpr-0.0.1.dist-info/RECORD
gpr-0.0.1.dist-info/WHEEL
gpr-0.0.1.dist-info/metadata.json
gpr-0.0.1.dist-info/top_level.txt
