Metadata-Version: 2.0
Name: gpr
Version: 0.0.1
Summary: Parse GCODE
Home-page: https://github.com/mindriot101/python-gpr
Author: Simon Walker
Author-email: s.r.walker101@googlemail.com
License: MIT
Platform: UNKNOWN
Classifier: Development Status :: 3 - Alpha
Classifier: Intended Audience :: Developers
Classifier: License :: OSI Approved :: MIT License
Classifier: Programming Language :: Python :: 2
Classifier: Programming Language :: Python :: 2.7
Classifier: Programming Language :: Python :: 3
Classifier: Programming Language :: Python :: 3.4
Classifier: Programming Language :: Python :: 3.5
Classifier: Programming Language :: Python :: 3.6
Requires-Dist: pybind11
